mailchimp3/__init__.py
mailchimp3/baseapi.py
mailchimp3/helpers.py
mailchimp3/mailchimpclient.py
mailchimp3/entities/__init__.py
mailchimp3/entities/authorizedapps.py
mailchimp3/entities/automationactions.py
mailchimp3/entities/automationemailactions.py
mailchimp3/entities/automationemailqueues.py
mailchimp3/entities/automationemails.py
mailchimp3/entities/automationremovedsubscribers.py
mailchimp3/entities/automations.py
mailchimp3/entities/batchoperations.py
mailchimp3/entities/batchwebhooks.py
mailchimp3/entities/campaignactions.py
mailchimp3/entities/campaigncontent.py
mailchimp3/entities/campaignfeedback.py
mailchimp3/entities/campaignfolders.py
mailchimp3/entities/campaigns.py
mailchimp3/entities/campaignsendchecklist.py
mailchimp3/entities/conversationmessages.py
mailchimp3/entities/conversations.py
mailchimp3/entities/customerjourney.py
mailchimp3/entities/filemanagerfiles.py
mailchimp3/entities/filemanagerfolders.py
mailchimp3/entities/landingpageaction.py
mailchimp3/entities/landingpagecontent.py
mailchimp3/entities/landingpages.py
mailchimp3/entities/listabusereports.py
mailchimp3/entities/listactivity.py
mailchimp3/entities/listclients.py
mailchimp3/entities/listgrowthhistory.py
mailchimp3/entities/listinterestcategories.py
mailchimp3/entities/listinterestcategoryinterest.py
mailchimp3/entities/listmemberactivity.py
mailchimp3/entities/listmemberevents.py
mailchimp3/entities/listmembergoals.py
mailchimp3/entities/listmembernotes.py
mailchimp3/entities/listmembers.py
mailchimp3/entities/listmembertags.py
mailchimp3/entities/listmergefields.py
mailchimp3/entities/lists.py
mailchimp3/entities/listsegmentmembers.py
mailchimp3/entities/listsegments.py
mailchimp3/entities/listsignupforms.py
mailchimp3/entities/listwebhooks.py
mailchimp3/entities/ping.py
mailchimp3/entities/reportcampaignabusereports.py
mailchimp3/entities/reportcampaignadvice.py
mailchimp3/entities/reportclickdetailmembers.py
mailchimp3/entities/reportclickdetailreports.py
mailchimp3-3.0.21.dist-info/LICENSE
mailchimp3-3.0.21.dist-info/METADATA
mailchimp3-3.0.21.dist-info/WHEEL
mailchimp3-3.0.21.dist-info/top_level.txt
mailchimp3-3.0.21.dist-info/RECORD
